Workbook

Sheet Summary
H3: =IF(H10=0,"Do not send until business purpose completed", "OK TO SEND") -> OK TO SEND
A7: EXPENSE REPORT SUMMARY
A9: Date From: | C9: 46062 | H9: Business Purpose of Travel
A10: Date to : | C10: 46064 | H10: In person team meetings
A12: NAME: | B12: Ted Power
A13: CURRENCY TO BE REIMBURSED IN: | G13: XEU
A14: TOTALS | B14: Base Currency | C14: Air Fares | D14: Hotel / Lodging | E14: Working Meals (Internal Staff) | F14: Taxis/Rail & Bus/Car Hire/Mileage | G14: Client Entertainment | H14: Marketing Related/Client travel | I14: PM travel supporting Sales | J14: Other | K14: Total
A15: FROM | C15: (A) | D15: (B) | E15: (C) | F15: (D) | G15: (E) | H15: (F) | I15: (G) | J15: (H) | K15: (A to H)
A16: PAGE | C16: =G13 -> XEU | D16: =G13 -> XEU | E16: =G13 -> XEU | F16: =G13 -> XEU | G16: =G13 -> XEU | H16: =G13 -> XEU | I16: =G13 -> XEU | J16: =G13 -> XEU | K16: =G13 -> XEU
A17: 1 | B17: =IF(Expenses!$J$6<>0,Expenses!$J$6,"") -> Euro | C17: =Expenses!E25 -> 401.15 | D17: =Expenses!F25 -> 589.6 | E17: =Expenses!G25 -> 331.47 | F17: =Expenses!H25 -> 93.5 | G17: =Expenses!I25 -> 0 | H17: =Expenses!J25 -> 0 | I17: =Expenses!K25 -> 0 | J17: =Expenses!L25 -> 0 | K17: =Expenses!M25 -> 1415.72
A18: 2 | B18: =IF('Expenses (2)'!J6<>0,'Expenses (2)'!J6,"") | C18: ='Expenses (2)'!E25 -> 0 | D18: ='Expenses (2)'!F25 -> 0 | E18: ='Expenses (2)'!G25 -> 0 | F18: ='Expenses (2)'!H25 -> 0 | G18: ='Expenses (2)'!I25 -> 0 | H18: ='Expenses (2)'!J25 -> 0 | I18: ='Expenses (2)'!K25 -> 0 | J18: ='Expenses (2)'!L25 -> 0 | K18: ='Expenses (2)'!M25 -> 0
A19: 3 | B19: =IF('Expenses (3)'!J6<>0,'Expenses (3)'!J6,"") | C19: ='Expenses (3)'!E25 -> 0 | D19: ='Expenses (3)'!F25 -> 0 | E19: ='Expenses (3)'!G25 -> 0 | F19: ='Expenses (3)'!H25 -> 0 | G19: ='Expenses (3)'!I25 -> 0 | H19: ='Expenses (3)'!J25 -> 0 | I19: ='Expenses (3)'!K25 -> 0 | J19: ='Expenses (3)'!L25 -> 0 | K19: ='Expenses (3)'!M25 -> 0
A20: 4 | B20: =IF('Expenses (4)'!J6<>0,'Expenses (4)'!J6,"") | C20: ='Expenses (4)'!E25 -> 0 | D20: ='Expenses (4)'!F25 -> 0 | E20: ='Expenses (4)'!G25 -> 0 | F20: ='Expenses (4)'!H25 -> 0 | G20: ='Expenses (4)'!I25 -> 0 | H20: ='Expenses (4)'!J25 -> 0 | I20: ='Expenses (4)'!K25 -> 0 | J20: ='Expenses (4)'!L25 -> 0 | K20: ='Expenses (4)'!M25 -> 0
A21: 5 | B21: =IF('Expenses (5)'!J6<>0,'Expenses (5)'!J6,"") | C21: ='Expenses (5)'!E25 -> 0 | D21: ='Expenses (5)'!F25 -> 0 | E21: ='Expenses (5)'!G25 -> 0 | F21: ='Expenses (5)'!H25 -> 0 | G21: ='Expenses (5)'!I25 -> 0 | H21: ='Expenses (5)'!J25 -> 0 | I21: ='Expenses (5)'!K25 -> 0 | J21: ='Expenses (5)'!L25 -> 0 | K21: ='Expenses (5)'!M25 -> 0
A22: 6 | B22: =IF('Expenses (6)'!J6<>0,'Expenses (6)'!J6,"") | C22: ='Expenses (6)'!E25 -> 0 | D22: ='Expenses (6)'!F25 -> 0 | E22: ='Expenses (6)'!G25 -> 0 | F22: ='Expenses (6)'!H25 -> 0 | G22: ='Expenses (6)'!I25 -> 0 | H22: ='Expenses (6)'!J25 -> 0 | I22: ='Expenses (6)'!K25 -> 0 | J22: ='Expenses (6)'!L25 -> 0 | K22: ='Expenses (6)'!M25 -> 0
A23: TOTAL | B23: =G13 -> XEU | C23: =SUM(C17:C22) -> 401.15 | D23: =SUM(D17:D22) -> 589.6 | E23: =SUM(E17:E22) -> 331.47 | F23: =SUM(F17:F22) -> 93.5 | G23: =SUM(G17:G22) -> 0 | H23: =SUM(H17:H22) -> 0 | I23: =SUM(I17:I22) -> 0 | J23: =SUM(J17:J22) -> 0 | K23: =SUM(K17:K22) -> 1415.72
A25: CODE | C25: 534020 | D25: 534030 | E25: 534045 | F25: 534060 | G25: 534040 | H25: 522101 | I25: 521700
H27: Deduct : Balance of cash advances o/s (€, £, $ xx)
H28: Bal. due to Employee | K28: =IF(K27+K23>0,K23+K27,"") -> 1415.72
A29: Reports prepared incorrectly or with inadequate | H29: or
A30: supporting documentation will be returned unprocessed. | H30: Bal. due to Amundi | K30: =IF(K27+K23<0,K27+K23,"")
A34: DECLARATION
A35: The expenses on this report are a bona fide and necessary operating expenditure properly supported by original documentation and properly incurred in
A36: accordance with Amundi Ireland Limited Business & Travel Expense Policy.
A38: __________________________________________ | F38: _______________________
A39: (Employee's signature) | F39: (date)
A41: APPROVAL
A42: I have reviewed this report for adherence to the Travel Expense Policy of Amundi Ireland Limited. and approve the reimbursement of the
A43: expenses claimed
A44: __________________________________________ | F44: _______________________
A45: (Approver's signature) | F45: (date)
A47: __________________________________________ | F47: _______________________
A48: (APPROVER'S NAME - BLOCK CAPITALS) | F48: (date)
A50: MISSING RECEIPTS
A51: There are items over €19.00 or equivalent NOT supported by ORIGINAL receipts. The Approvers attention has been drawn to these items and the explanation has
A52: been accepted. Where a receipt is missing for an item in excess of €63.50 or equivalent an explanatory memo is enclosed.
A54: __________________________________________
A55: (Employee's signature)
A57: __________________________________________
A58: (Approver's signature)

Sheet Expenses
A1: EXPENSE REPORT DETAIL
B2: Only original receipts accepted. Credit Card receipts or statements cannot be used in lieu of original receipts.
L4: Page | M4: 1
A6: Name: | C6: Kevin Breen | H6: Currency Incurred : | J6: Euro | K6: FX Rate : | L6: XEU | M6: 1
A7: Receipt No. | B7: Date | C7: Location | D7: BUSINESS PURPOSE & DETAILS | E7: =Summary!C14 -> Air Fares | F7: =Summary!D14 -> Hotel / Lodging | G7: =Summary!E14 -> Working Meals (Internal Staff) | H7: =Summary!F14 -> Taxis/Rail & Bus/Car Hire/Mileage | I7: =Summary!G14 -> Client Entertainment | J7: =Summary!H14 -> Marketing Related/Client travel | K7: =Summary!I14 -> PM travel supporting Sales | L7: =Summary!J14 -> Other | M7: Total
D8: (Nature of expenditure, Guest names, Company Affiliations, etc) Please attach further details on separate sheet if necessary | E8: (A) | F8: (B) | G8: (C) | H8: (D) | I8: (E) | J8: (F) | K8: (G) | L8: (H) | M8: (A thru H)
A9: 1 | B9: 46062 | C9: Dublin | D9: Vueling - Dublin to France | E9: 63.99 | M9: =SUM(E9:L9) -> 63.99
A10: 2 | B10: 46062 | C10: Paris | D10: Mercure Paris Notre Dame | F10: 589.6 | M10: =SUM(E10:L10) -> 589.6
A11: 3 | B11: 46062 | C11: Paris | D11: Dublin Airport Food | G11: 9.82 | M11: =SUM(E11:L11) -> 9.82
A12: 4 | B12: 46063 | C12: Paris | D12: Dinner - Boulom with Riccardo Monzani, Jerome Esnee, Franck Dequeeker, Roy Chrabieh, Jean-David N'Diaye, Franck Wetie, Herve Yesilyurt | G12: 302.5 | M12: =SUM(E12:L12) -> 302.5
A13: 5 | B13: 46063 | C13: Paris | D13: Metro Paris | H13: 2.55 | M13: =SUM(E13:L13) -> 2.55
A14: 6 | B14: 46063 | C14: Paris | D14: Metro Paris | H14: 2.55 | M14: =SUM(E14:L14) -> 2.55
A15: 7 | B15: 46064 | C15: Paris | D15: Metro Paris to CDG | H15: 14 | M15: =SUM(E15:L15) -> 14
A16: 8 | B16: 46064 | C16: Paris | D16: Food CDG Airport | G16: 19.15 | M16: =SUM(E16:L16) -> 19.15
A17: 9 | B17: 46064 | C17: Paris | D17: Air France - CDG to DUB | E17: 316.17 | M17: =SUM(E17:L17) -> 316.17
A18: 10 | B18: 46064 | C18: Paris | D18: Air France - CDG to DUB - seat assignment | E18: 20.99 | M18: =SUM(E18:L18) -> 20.99
A19: 11 | B19: 46064 | C19: Paris | D19: Taxi - Dublin Airport to home | H19: 74.4 | M19: =SUM(E19:L19) -> 74.4
A20: 12 | M20: =SUM(E20:L20) -> 0
A21: 13 | M21: =SUM(E21:L21) -> 0
M22: =SUM(E22:L22) -> 0
M23: =SUM(E23:L23) -> 0
C24: Total | D24: Base Currency | E24: =SUM(E9:E23) -> 401.15 | F24: =SUM(F9:F23) -> 589.6 | G24: =SUM(G9:G23) -> 331.47 | H24: =SUM(H9:H23) -> 93.5 | I24: =SUM(I9:I23) -> 0 | J24: =SUM(J9:J23) -> 0 | K24: =SUM(K9:K23) -> 0 | L24: =SUM(L9:L23) -> 0 | ... N24: =SUM(N9:N23) -> 0
C25: Total | D25: =Summary!G13 -> XEU | E25: =E24/$M$6 -> 401.15 | F25: =F24/$M$6 -> 589.6 | G25: =G24/$M$6 -> 331.47 | H25: =H24/$M$6 -> 93.5 | I25: =I24/$M$6 -> 0 | J25: =J24/$M$6 -> 0 | K25: =K24/$M$6 -> 0 | L25: =L24/$M$6 -> 0 | M25: =M24/$M$6 -> 1415.72

Sheet Expenses (2)
A1: EXPENSE REPORT DETAIL
B2: Only original receipts accepted. Credit Card receipts or statements cannot be used in lieu of original receipts.
L4: Page | M4: 2
A6: Name: | H6: Currency Incurred : | K6: FX Rate : | L6: XEU | M6: 1
A7: Receipt No. | B7: Date | C7: Location | D7: BUSINESS PURPOSE & DETAILS | E7: =Summary!C14 -> Air Fares | F7: =Summary!D14 -> Hotel / Lodging | G7: =Summary!E14 -> Working Meals (Internal Staff) | H7: =Summary!F14 -> Taxis/Rail & Bus/Car Hire/Mileage | I7: =Summary!G14 -> Client Entertainment | J7: =Summary!H14 -> Marketing Related/Client travel | K7: =Summary!I14 -> PM travel supporting Sales | L7: =Summary!J14 -> Other | M7: Total
D8: (Nature of expenditure, Guest names, Company Affiliations, etc) Please attach further details on separate sheet if necessary | E8: (A) | F8: (B) | G8: (C) | H8: (D) | I8: (E) | J8: (F) | K8: (G) | L8: (H) | M8: (A thru H)
M9: =SUM(E9:L9) -> 0
M10: =SUM(E10:L10) -> 0
M11: =SUM(E11:L11) -> 0
M12: =SUM(E12:L12) -> 0
M13: =SUM(E13:L13) -> 0
M14: =SUM(E14:L14) -> 0
M15: =SUM(E15:L15) -> 0
M16: =SUM(E16:L16) -> 0
M17: =SUM(E17:L17) -> 0
M18: =SUM(E18:L18) -> 0
M19: =SUM(E19:L19) -> 0
M20: =SUM(E20:L20) -> 0
... M23: =SUM(E23:L23) -> 0
C24: Total | D24: Base Currency | E24: =SUM(E9:E23) -> 0 | F24: =SUM(F9:F23) -> 0 | G24: =SUM(G9:G23) -> 0 | H24: =SUM(H9:H23) -> 0 | I24: =SUM(I9:I23) -> 0 | J24: =SUM(J9:J23) -> 0 | K24: =SUM(K9:K23) -> 0 | L24: =SUM(L9:L23) -> 0 | ... N24: =SUM(N9:N23) -> 0
C25: Total | D25: =Summary!G13 -> XEU | E25: =E24/$M$6 -> 0 | F25: =F24/$M$6 -> 0 | G25: =G24/$M$6 -> 0 | H25: =H24/$M$6 -> 0 | I25: =I24/$M$6 -> 0 | J25: =J24/$M$6 -> 0 | K25: =K24/$M$6 -> 0 | L25: =L24/$M$6 -> 0 | M25: =M24/$M$6 -> 0

Sheet Expenses (3)
A1: EXPENSE REPORT DETAIL
B2: Only original receipts accepted. Credit Card receipts or statements cannot be used in lieu of original receipts.
L4: Page | M4: 3
A6: Name: | H6: Currency Incurred : | K6: FX Rate : | L6: XEU | M6: 1
A7: Receipt No. | B7: Date | C7: Location | D7: BUSINESS PURPOSE & DETAILS | E7: =Summary!C14 -> Air Fares | F7: =Summary!D14 -> Hotel / Lodging | G7: =Summary!E14 -> Working Meals (Internal Staff) | H7: =Summary!F14 -> Taxis/Rail & Bus/Car Hire/Mileage | I7: =Summary!G14 -> Client Entertainment | J7: =Summary!H14 -> Marketing Related/Client travel | K7: =Summary!I14 -> PM travel supporting Sales | L7: =Summary!J14 -> Other | M7: Total
D8: (Nature of expenditure, Guest names, Company Affiliations, etc) Please attach further details on separate sheet if necessary | E8: (A) | F8: (B) | G8: (C) | H8: (D) | I8: (E) | J8: (F) | K8: (G) | L8: (H) | M8: (A thru H)
M9: =SUM(E9:L9) -> 0
M10: =SUM(E10:L10) -> 0
M11: =SUM(E11:L11) -> 0
M12: =SUM(E12:L12) -> 0
M13: =SUM(E13:L13) -> 0
M14: =SUM(E14:L14) -> 0
M15: =SUM(E15:L15) -> 0
M16: =SUM(E16:L16) -> 0
M17: =SUM(E17:L17) -> 0
M18: =SUM(E18:L18) -> 0
M19: =SUM(E19:L19) -> 0
M20: =SUM(E20:L20) -> 0
... M23: =SUM(E23:L23) -> 0
C24: Total | D24: Base Currency | E24: =SUM(E9:E23) -> 0 | F24: =SUM(F9:F23) -> 0 | G24: =SUM(G9:G23) -> 0 | H24: =SUM(H9:H23) -> 0 | I24: =SUM(I9:I23) -> 0 | J24: =SUM(J9:J23) -> 0 | K24: =SUM(K9:K23) -> 0 | L24: =SUM(L9:L23) -> 0 | ... N24: =SUM(N9:N23) -> 0
C25: Total | D25: =Summary!G13 -> XEU | E25: =E24/$M$6 -> 0 | F25: =F24/$M$6 -> 0 | G25: =G24/$M$6 -> 0 | H25: =H24/$M$6 -> 0 | I25: =I24/$M$6 -> 0 | J25: =J24/$M$6 -> 0 | K25: =K24/$M$6 -> 0 | L25: =L24/$M$6 -> 0 | M25: =M24/$M$6 -> 0

Sheet Expenses (4)
A1: EXPENSE REPORT DETAIL
B2: Only original receipts accepted. Credit Card receipts or statements cannot be used in lieu of original receipts.
L4: Page | M4: 4
A6: Name: | H6: Currency Incurred : | K6: FX Rate : | L6: XEU | M6: 1
A7: Receipt No. | B7: Date | C7: Location | D7: BUSINESS PURPOSE & DETAILS | E7: =Summary!C14 -> Air Fares | F7: =Summary!D14 -> Hotel / Lodging | G7: =Summary!E14 -> Working Meals (Internal Staff) | H7: =Summary!F14 -> Taxis/Rail & Bus/Car Hire/Mileage | I7: =Summary!G14 -> Client Entertainment | J7: =Summary!H14 -> Marketing Related/Client travel | K7: =Summary!I14 -> PM travel supporting Sales | L7: =Summary!J14 -> Other | M7: Total
D8: (Nature of expenditure, Guest names, Company Affiliations, etc) Please attach further details on separate sheet if necessary | E8: (A) | F8: (B) | G8: (C) | H8: (D) | I8: (E) | J8: (F) | K8: (G) | L8: (H) | M8: (A thru H)
M9: =SUM(E9:L9) -> 0
M10: =SUM(E10:L10) -> 0
M11: =SUM(E11:L11) -> 0
M12: =SUM(E12:L12) -> 0
M13: =SUM(E13:L13) -> 0
M14: =SUM(E14:L14) -> 0
M15: =SUM(E15:L15) -> 0
M16: =SUM(E16:L16) -> 0
M17: =SUM(E17:L17) -> 0
M18: =SUM(E18:L18) -> 0
M19: =SUM(E19:L19) -> 0
M20: =SUM(E20:L20) -> 0
... M23: =SUM(E23:L23) -> 0
C24: Total | D24: Base Currency | E24: =SUM(E9:E23) -> 0 | F24: =SUM(F9:F23) -> 0 | G24: =SUM(G9:G23) -> 0 | H24: =SUM(H9:H23) -> 0 | I24: =SUM(I9:I23) -> 0 | J24: =SUM(J9:J23) -> 0 | K24: =SUM(K9:K23) -> 0 | L24: =SUM(L9:L23) -> 0 | ... N24: =SUM(N9:N23) -> 0
C25: Total | D25: =Summary!G13 -> XEU | E25: =E24/$M$6 -> 0 | F25: =F24/$M$6 -> 0 | G25: =G24/$M$6 -> 0 | H25: =H24/$M$6 -> 0 | I25: =I24/$M$6 -> 0 | J25: =J24/$M$6 -> 0 | K25: =K24/$M$6 -> 0 | L25: =L24/$M$6 -> 0 | M25: =M24/$M$6 -> 0

Sheet Expenses (5)
A1: EXPENSE REPORT DETAIL
B2: Only original receipts accepted. Credit Card receipts or statements cannot be used in lieu of original receipts.
L4: Page | M4: 5
A6: Name: | H6: Currency Incurred : | K6: FX Rate : | L6: XEU | M6: 1
A7: Receipt No. | B7: Date | C7: Location | D7: BUSINESS PURPOSE & DETAILS | E7: =Summary!C14 -> Air Fares | F7: =Summary!D14 -> Hotel / Lodging | G7: =Summary!E14 -> Working Meals (Internal Staff) | H7: =Summary!F14 -> Taxis/Rail & Bus/Car Hire/Mileage | I7: =Summary!G14 -> Client Entertainment | J7: =Summary!H14 -> Marketing Related/Client travel | K7: =Summary!I14 -> PM travel supporting Sales | L7: =Summary!J14 -> Other | M7: Total
D8: (Nature of expenditure, Guest names, Company Affiliations, etc) Please attach further details on separate sheet if necessary | E8: (A) | F8: (B) | G8: (C) | H8: (D) | I8: (E) | J8: (F) | K8: (G) | L8: (H) | M8: (A thru H)
M9: =SUM(E9:L9) -> 0
M10: =SUM(E10:L10) -> 0
M11: =SUM(E11:L11) -> 0
M12: =SUM(E12:L12) -> 0
M13: =SUM(E13:L13) -> 0
M14: =SUM(E14:L14) -> 0
M15: =SUM(E15:L15) -> 0
M16: =SUM(E16:L16) -> 0
M17: =SUM(E17:L17) -> 0
M18: =SUM(E18:L18) -> 0
M19: =SUM(E19:L19) -> 0
M20: =SUM(E20:L20) -> 0
... M23: =SUM(E23:L23) -> 0
C24: Total | D24: Base Currency | E24: =SUM(E9:E23) -> 0 | F24: =SUM(F9:F23) -> 0 | G24: =SUM(G9:G23) -> 0 | H24: =SUM(H9:H23) -> 0 | I24: =SUM(I9:I23) -> 0 | J24: =SUM(J9:J23) -> 0 | K24: =SUM(K9:K23) -> 0 | L24: =SUM(L9:L23) -> 0 | ... N24: =SUM(N9:N23) -> 0
C25: Total | D25: =Summary!G13 -> XEU | E25: =E24/$M$6 -> 0 | F25: =F24/$M$6 -> 0 | G25: =G24/$M$6 -> 0 | H25: =H24/$M$6 -> 0 | I25: =I24/$M$6 -> 0 | J25: =J24/$M$6 -> 0 | K25: =K24/$M$6 -> 0 | L25: =L24/$M$6 -> 0 | M25: =M24/$M$6 -> 0

Sheet Expenses (6)
A1: EXPENSE REPORT DETAIL
B2: Only original receipts accepted. Credit Card receipts or statements cannot be used in lieu of original receipts.
L4: Page | M4: 6
A6: Name: | H6: Currency Incurred : | K6: FX Rate : | L6: XEU | M6: 1
A7: Receipt No. | B7: Date | C7: Location | D7: BUSINESS PURPOSE & DETAILS | E7: =Summary!C14 -> Air Fares | F7: =Summary!D14 -> Hotel / Lodging | G7: =Summary!E14 -> Working Meals (Internal Staff) | H7: =Summary!F14 -> Taxis/Rail & Bus/Car Hire/Mileage | I7: =Summary!G14 -> Client Entertainment | J7: =Summary!H14 -> Marketing Related/Client travel | K7: =Summary!I14 -> PM travel supporting Sales | L7: =Summary!J14 -> Other | M7: Total
D8: (Nature of expenditure, Guest names, Company Affiliations, etc) Please attach further details on separate sheet if necessary | E8: (A) | F8: (B) | G8: (C) | H8: (D) | I8: (E) | J8: (F) | K8: (G) | L8: (H) | M8: (A thru H)
M9: =SUM(E9:L9) -> 0
M10: =SUM(E10:L10) -> 0
M11: =SUM(E11:L11) -> 0
M12: =SUM(E12:L12) -> 0
M13: =SUM(E13:L13) -> 0
M14: =SUM(E14:L14) -> 0
M15: =SUM(E15:L15) -> 0
M16: =SUM(E16:L16) -> 0
M17: =SUM(E17:L17) -> 0
M18: =SUM(E18:L18) -> 0
M19: =SUM(E19:L19) -> 0
M20: =SUM(E20:L20) -> 0
... M23: =SUM(E23:L23) -> 0
C24: Total | D24: Base Currency | E24: =SUM(E9:E23) -> 0 | F24: =SUM(F9:F23) -> 0 | G24: =SUM(G9:G23) -> 0 | H24: =SUM(H9:H23) -> 0 | I24: =SUM(I9:I23) -> 0 | J24: =SUM(J9:J23) -> 0 | K24: =SUM(K9:K23) -> 0 | L24: =SUM(L9:L23) -> 0 | ... N24: =SUM(N9:N23) -> 0
C25: Total | D25: =Summary!G13 -> XEU | E25: =E24/$M$6 -> 0 | F25: =F24/$M$6 -> 0 | G25: =G24/$M$6 -> 0 | H25: =H24/$M$6 -> 0 | I25: =I24/$M$6 -> 0 | J25: =J24/$M$6 -> 0 | K25: =K24/$M$6 -> 0 | L25: =L24/$M$6 -> 0 | M25: =M24/$M$6 -> 0
